MANIFEST.in
README
setup.py
pyallpairs.egg-info/PKG-INFO
pyallpairs.egg-info/SOURCES.txt
pyallpairs.egg-info/dependency_links.txt
pyallpairs.egg-info/top_level.txt
src/__init__.py
src/allpairs.cc
src/allpairs.h
src/allpairs.i
src/allpairs.py
src/data-source-iterator.cc
src/data-source-iterator.h