Metadata-Version: 1.1
Name: pyallpairs
Version: 0.1.0
Summary: Python bindings for the Google All Pairs Similarity Search
Home-page: https://github.com/phoenix24/google-all-pairs-similarity-search
Author: Chaitanya Sharma
Author-email: chaitanya@3bandar.org
License: Apache License 2.0
Platform: UNKNOWN
Classifier: Development Status :: 5 - Production/Stable
Classifier: Environment :: Console
Classifier: Intended Audience :: Developers
Classifier: Programming Language :: Python
Classifier: Programming Language :: Python :: 2
Classifier: Topic :: Software Development :: Libraries
